{"lastUpdated":1643967161069,"pendingReflectionsLastTwoHoursInUSD":24.381068240787,"pendingReflectionsLastTwoHoursInETH":0.008613346654626998,"pendingReflectionsLastTwentyFourHoursInUSD":2638.2796479786625,"pendingReflectionsLastTwentyFourHoursInETH":0.9320517442247225,"circulatingICYSupplyInUSD":621800.4717262512,"liquidityInUSD":88936.98989526881,"treasuryValueInUSD":20455.82064367633,"insurancePercentage":0.2300035189831011,"reflectionTreasuryBalanceInUSD":88936.95604663776,"reflectionTreasuryBalanceInETH":31.419658288618468,"circulatingICYSupply":726245502399115.6,"pricePerETH":"2830.615","pricePerAVAX":"71.665","pricePerICY":8.56184953534534e-10,"ICYMarketCap":856184.9535345341,"ICY2HourVolume":4527.347891002611,"ICY24HourVolume":16041.82,"ETHDistributedInUSD":292162.7244295203,"ETHDistributed":103.2603342179277,"deposits":[0,544.49946194968,48.94394976461461,212.97380789745213,136.98394462869237],"planetData":{"96":{"rewardMult":"4% + 0.00% BONUS","planetValue":"4530676","dailyRewards":"181227","totalClaimed":"1031091","tofuLink":"https://tofunft.com/nft/avax/0x89323f00a621D4eD6A56a93295C5f10f4df57FFa/96"},"503":{"rewardMult":"4% + 0.00% BONUS","planetValue":"5572257","dailyRewards":"222890","totalClaimed":"1335491","tofuLink":"https://tofunft.com/nft/avax/0x89323f00a621D4eD6A56a93295C5f10f4df57FFa/503"},"566":{"rewardMult":"4% + 0.00% BONUS","planetValue":"5138024","dailyRewards":"205521","totalClaimed":"1816304","tofuLink":"https://tofunft.com/nft/avax/0x89323f00a621D4eD6A56a93295C5f10f4df57FFa/566"},"766":{"rewardMult":"4% + 0.00% BONUS","planetValue":"4596551","dailyRewards":"183862","totalClaimed":"1048105","tofuLink":"https://tofunft.com/nft/avax/0x89323f00a621D4eD6A56a93295C5f10f4df57FFa/766"}}}