{"lastUpdated":1645379600646,"pendingReflectionsLastTwoHoursInUSD":63.48348386820069,"pendingReflectionsLastTwoHoursInETH":0.02395196433367945,"pendingReflectionsLastTwentyFourHoursInUSD":257.8763845258924,"pendingReflectionsLastTwentyFourHoursInETH":0.09729532137029274,"circulatingICYSupplyInUSD":279931.5347643134,"liquidityInUSD":63054.516983565314,"treasuryValueInUSD":19417.44416785508,"insurancePercentage":0.30794691794905177,"reflectionTreasuryBalanceInUSD":63074.369761945614,"reflectionTreasuryBalanceInETH":23.797607863549818,"circulatingICYSupply":721784282535530.8,"pricePerETH":"2650.45","pricePerAVAX":"79.28","pricePerICY":3.8783268289100404e-10,"ICYMarketCap":387832.682891004,"ICY2HourVolume":335.24958543055,"ICY24HourVolume":1416.14,"ETHDistributedInUSD":282070.4950564735,"ETHDistributed":106.423624311522,"deposits":[0,908.4630036066588,142.98204453181694,343.19975240326323,217.9446302117844],"planetData":{"96":{"rewardMult":"4% + 0.00% BONUS","planetValue":"4530676","dailyRewards":"181227","totalClaimed":"2950149","tofuLink":"https://tofunft.com/nft/avax/0x89323f00a621D4eD6A56a93295C5f10f4df57FFa/96"},"503":{"rewardMult":"4% + 0.00% BONUS","planetValue":"5572257","dailyRewards":"222890","totalClaimed":"3695732","tofuLink":"https://tofunft.com/nft/avax/0x89323f00a621D4eD6A56a93295C5f10f4df57FFa/503"},"566":{"rewardMult":"4% + 0.00% BONUS","planetValue":"5138024","dailyRewards":"205521","totalClaimed":"3992617","tofuLink":"https://tofunft.com/nft/avax/0x89323f00a621D4eD6A56a93295C5f10f4df57FFa/566"},"766":{"rewardMult":"4% + 0.00% BONUS","planetValue":"4596551","dailyRewards":"183862","totalClaimed":"2995066","tofuLink":"https://tofunft.com/nft/avax/0x89323f00a621D4eD6A56a93295C5f10f4df57FFa/766"}}}