{"lastUpdated":1645128213969,"pendingReflectionsLastTwoHoursInUSD":0,"pendingReflectionsLastTwoHoursInETH":0,"pendingReflectionsLastTwentyFourHoursInUSD":690.3666776568523,"pendingReflectionsLastTwentyFourHoursInETH":0.23733442345710645,"circulatingICYSupplyInUSD":328280.6870945611,"liquidityInUSD":71932.59156715454,"treasuryValueInUSD":21453.855453694567,"insurancePercentage":0.2982494441850571,"reflectionTreasuryBalanceInUSD":71932.55023649293,"reflectionTreasuryBalanceInETH":24.728989522091464,"circulatingICYSupply":723323937006477.9,"pricePerETH":"2908.835","pricePerAVAX":"88.125","pricePerICY":4.538501635286282e-10,"ICYMarketCap":453850.1635286282,"ICY2HourVolume":196.54788822425598,"ICY24HourVolume":5175.37,"ETHDistributedInUSD":309568.7632242061,"ETHDistributed":106.423624311522,"deposits":[0,935.9511623334809,146.57813472701065,351.83144648368454,223.42607757216845],"planetData":{"96":{"rewardMult":"4% + 0.00% BONUS","planetValue":"4530676","dailyRewards":"181227","totalClaimed":"2702910","tofuLink":"https://tofunft.com/nft/avax/0x89323f00a621D4eD6A56a93295C5f10f4df57FFa/96"},"503":{"rewardMult":"4% + 0.00% BONUS","planetValue":"5572257","dailyRewards":"222890","totalClaimed":"3391654","tofuLink":"https://tofunft.com/nft/avax/0x89323f00a621D4eD6A56a93295C5f10f4df57FFa/503"},"566":{"rewardMult":"4% + 0.00% BONUS","planetValue":"5138024","dailyRewards":"205521","totalClaimed":"3712235","tofuLink":"https://tofunft.com/nft/avax/0x89323f00a621D4eD6A56a93295C5f10f4df57FFa/566"},"766":{"rewardMult":"4% + 0.00% BONUS","planetValue":"4596551","dailyRewards":"183862","totalClaimed":"2744232","tofuLink":"https://tofunft.com/nft/avax/0x89323f00a621D4eD6A56a93295C5f10f4df57FFa/766"}}}