{"lastUpdated":1644228735798,"pendingReflectionsLastTwoHoursInUSD":0,"pendingReflectionsLastTwoHoursInETH":0,"pendingReflectionsLastTwentyFourHoursInUSD":1414.4794035348336,"pendingReflectionsLastTwentyFourHoursInETH":0.4610405762471284,"circulatingICYSupplyInUSD":531957.7955739012,"liquidityInUSD":87884.82202024655,"treasuryValueInUSD":16808.8042852504,"insurancePercentage":0.1912594677767915,"reflectionTreasuryBalanceInUSD":87830.94904286748,"reflectionTreasuryBalanceInETH":28.627939903444894,"circulatingICYSupply":725674973929215.4,"pricePerETH":"3068.015","pricePerAVAX":"81.575","pricePerICY":7.330524197266722e-10,"ICYMarketCap":733052.4197266722,"ICY2HourVolume":181.50263502874202,"ICY24HourVolume":9397.63,"ETHDistributedInUSD":318645.6040284166,"ETHDistributed":103.81144728101367,"deposits":[0,843.4144302997335,95.1897108892535,281.478640969363,181.04599359528964],"planetData":{"96":{"rewardMult":"4% + 0.00% BONUS","planetValue":"4530676","dailyRewards":"181227","totalClaimed":"1493401","tofuLink":"https://tofunft.com/nft/avax/0x89323f00a621D4eD6A56a93295C5f10f4df57FFa/96"},"503":{"rewardMult":"4% + 0.00% BONUS","planetValue":"5572257","dailyRewards":"222890","totalClaimed":"1904084","tofuLink":"https://tofunft.com/nft/avax/0x89323f00a621D4eD6A56a93295C5f10f4df57FFa/503"},"566":{"rewardMult":"4% + 0.00% BONUS","planetValue":"5138024","dailyRewards":"205521","totalClaimed":"2340588","tofuLink":"https://tofunft.com/nft/avax/0x89323f00a621D4eD6A56a93295C5f10f4df57FFa/566"},"766":{"rewardMult":"4% + 0.00% BONUS","planetValue":"4596551","dailyRewards":"183862","totalClaimed":"1517137","tofuLink":"https://tofunft.com/nft/avax/0x89323f00a621D4eD6A56a93295C5f10f4df57FFa/766"}}}