{"lastUpdated":1644292959524,"pendingReflectionsLastTwoHoursInUSD":0,"pendingReflectionsLastTwoHoursInETH":0,"pendingReflectionsLastTwentyFourHoursInUSD":1908.9042252398083,"pendingReflectionsLastTwentyFourHoursInETH":0.6061370005794339,"circulatingICYSupplyInUSD":564448.5471307778,"liquidityInUSD":95309.9552835705,"treasuryValueInUSD":25527.46751564025,"insurancePercentage":0.2678363182491249,"reflectionTreasuryBalanceInUSD":95309.91280304709,"reflectionTreasuryBalanceInETH":30.26388852204925,"circulatingICYSupply":724645124828633.2,"pricePerETH":"3149.295","pricePerAVAX":"90.465","pricePerICY":7.789309936560474e-10,"ICYMarketCap":778930.9936560474,"ICY2HourVolume":1185.0338984253378,"ICY24HourVolume":15003.8,"ETHDistributedInUSD":327511.2708885154,"ETHDistributed":103.99510712350396,"deposits":[0,833.178956052745,94.33048092176075,278.9378738854602,237.30914813539346],"planetData":{"96":{"rewardMult":"4% + 0.00% BONUS","planetValue":"4530676","dailyRewards":"181227","totalClaimed":"1561588","tofuLink":"https://tofunft.com/nft/avax/0x89323f00a621D4eD6A56a93295C5f10f4df57FFa/96"},"503":{"rewardMult":"4% + 0.00% BONUS","planetValue":"5572257","dailyRewards":"222890","totalClaimed":"1987946","tofuLink":"https://tofunft.com/nft/avax/0x89323f00a621D4eD6A56a93295C5f10f4df57FFa/503"},"566":{"rewardMult":"4% + 0.00% BONUS","planetValue":"5138024","dailyRewards":"205521","totalClaimed":"2417916","tofuLink":"https://tofunft.com/nft/avax/0x89323f00a621D4eD6A56a93295C5f10f4df57FFa/566"},"766":{"rewardMult":"4% + 0.00% BONUS","planetValue":"4596551","dailyRewards":"183862","totalClaimed":"1586315","tofuLink":"https://tofunft.com/nft/avax/0x89323f00a621D4eD6A56a93295C5f10f4df57FFa/766"}}}