{"lastUpdated":1643321627895,"pendingReflectionsLastTwoHoursInUSD":0,"pendingReflectionsLastTwoHoursInETH":0,"pendingReflectionsLastTwentyFourHoursInUSD":5073.433696365642,"pendingReflectionsLastTwentyFourHoursInETH":2.1605444534011475,"circulatingICYSupplyInUSD":817320.289167002,"liquidityInUSD":92705.07223484498,"treasuryValueInUSD":19197.004790863222,"insurancePercentage":0.20707609980856753,"reflectionTreasuryBalanceInUSD":93196.7688487392,"reflectionTreasuryBalanceInETH":39.68826125692619,"circulatingICYSupply":727341299283071.4,"pricePerETH":"2348.22","pricePerAVAX":"62.545","pricePerICY":1.1237094469578744e-9,"ICYMarketCap":1123709.4469578743,"ICY2HourVolume":1180.5545771902296,"ICY24HourVolume":41438.03,"ETHDistributedInUSD":232616.92524124225,"ETHDistributed":99.06095904184542,"deposits":[0,452.02988638129,0,3.1469e-7,0]}