{"lastUpdated":1644509613847,"pendingReflectionsLastTwoHoursInUSD":0,"pendingReflectionsLastTwoHoursInETH":0,"pendingReflectionsLastTwentyFourHoursInUSD":1976.8220659998735,"pendingReflectionsLastTwentyFourHoursInETH":0.6161011238546013,"circulatingICYSupplyInUSD":554140.3711622162,"liquidityInUSD":95471.96370464798,"treasuryValueInUSD":27175.740485455488,"insurancePercentage":0.28464629228247934,"reflectionTreasuryBalanceInUSD":95760.66660419197,"reflectionTreasuryBalanceInETH":29.844999876641516,"circulatingICYSupply":724220641947246.8,"pricePerETH":"3208.6","pricePerAVAX":"92.86","pricePerICY":7.651540691691311e-10,"ICYMarketCap":765154.0691691311,"ICY2HourVolume":447.37673801133076,"ICY24HourVolume":12494.33,"ETHDistributedInUSD":336394.64130962203,"ETHDistributed":104.93084289432261,"deposits":[0,888.2155429539505,91.9181522583094,271.804550447109,231.24040284154614],"planetData":{"96":{"rewardMult":"4% + 0.00% BONUS","planetValue":"4530676","dailyRewards":"181227","totalClaimed":"1919738","tofuLink":"https://tofunft.com/nft/avax/0x89323f00a621D4eD6A56a93295C5f10f4df57FFa/96"},"503":{"rewardMult":"4% + 0.00% BONUS","planetValue":"5572257","dailyRewards":"222890","totalClaimed":"2428433","tofuLink":"https://tofunft.com/nft/avax/0x89323f00a621D4eD6A56a93295C5f10f4df57FFa/503"},"566":{"rewardMult":"4% + 0.00% BONUS","planetValue":"5138024","dailyRewards":"205521","totalClaimed":"2824076","tofuLink":"https://tofunft.com/nft/avax/0x89323f00a621D4eD6A56a93295C5f10f4df57FFa/566"},"766":{"rewardMult":"4% + 0.00% BONUS","planetValue":"4596551","dailyRewards":"183862","totalClaimed":"1949673","tofuLink":"https://tofunft.com/nft/avax/0x89323f00a621D4eD6A56a93295C5f10f4df57FFa/766"}}}