{"lastUpdated":1643682807456,"pendingReflectionsLastTwoHoursInUSD":7.2080137549570535,"pendingReflectionsLastTwoHoursInETH":0.002670569423356343,"pendingReflectionsLastTwentyFourHoursInUSD":1360.1268640143671,"pendingReflectionsLastTwentyFourHoursInETH":0.5039270648483885,"circulatingICYSupplyInUSD":716513.5014701263,"liquidityInUSD":92191.6021852875,"treasuryValueInUSD":17975.13456187224,"insurancePercentage":0.19497583441218058,"reflectionTreasuryBalanceInUSD":92204.8183787413,"reflectionTreasuryBalanceInETH":34.161889394155104,"circulatingICYSupply":726605306999406.2,"pricePerETH":"2699.055","pricePerAVAX":"69.6","pricePerICY":9.86111021441675e-10,"ICYMarketCap":986111.0214416749,"ICY2HourVolume":114.64774484385147,"ICY24HourVolume":10490.07,"ETHDistributedInUSD":274014.72193574463,"ETHDistributed":101.5224669136956,"deposits":[0,574.99608031704,54.3885317602191,170.40723334857915,63.98424164016138],"planetData":{"96":{"rewardMult":"4% + 0.00% BONUS","planetValue":"4530676","dailyRewards":"181227","totalClaimed":"424841","tofuLink":"https://tofunft.com/nft/avax/0x89323f00a621D4eD6A56a93295C5f10f4df57FFa/96"},"503":{"rewardMult":"4% + 0.00% BONUS","planetValue":"5572257","dailyRewards":"222890","totalClaimed":"589867","tofuLink":"https://tofunft.com/nft/avax/0x89323f00a621D4eD6A56a93295C5f10f4df57FFa/503"},"566":{"rewardMult":"4% + 0.00% BONUS","planetValue":"5138024","dailyRewards":"205521","totalClaimed":"1128785","tofuLink":"https://tofunft.com/nft/avax/0x89323f00a621D4eD6A56a93295C5f10f4df57FFa/566"},"766":{"rewardMult":"4% + 0.00% BONUS","planetValue":"4596551","dailyRewards":"183862","totalClaimed":"433041","tofuLink":"https://tofunft.com/nft/avax/0x89323f00a621D4eD6A56a93295C5f10f4df57FFa/766"}}}