{"lastUpdated":1645457599486,"pendingReflectionsLastTwoHoursInUSD":0,"pendingReflectionsLastTwoHoursInETH":0,"pendingReflectionsLastTwentyFourHoursInUSD":508.77370490562373,"pendingReflectionsLastTwentyFourHoursInETH":0.18685611735876675,"circulatingICYSupplyInUSD":287484.7006367077,"liquidityInUSD":63579.55102122044,"treasuryValueInUSD":25709.699231507242,"insurancePercentage":0.4043705691304162,"reflectionTreasuryBalanceInUSD":63563.334078692664,"reflectionTreasuryBalanceInETH":23.344755630650933,"circulatingICYSupply":723480383013801.2,"pricePerETH":"2722.81","pricePerAVAX":"78.57","pricePerICY":3.9736350478382437e-10,"ICYMarketCap":397363.5047838244,"ICY2HourVolume":65.79796493869861,"ICY24HourVolume":3765.69,"ETHDistributedInUSD":290607.35875904333,"ETHDistributed":106.63140217441952,"deposits":[0,928.111828082693,145.486464489184,349.21111076330766,221.7620667489458],"planetData":{"96":{"rewardMult":"4% + 0.00% BONUS","planetValue":"4530676","dailyRewards":"181227","totalClaimed":"2989702","tofuLink":"https://tofunft.com/nft/avax/0x89323f00a621D4eD6A56a93295C5f10f4df57FFa/96"},"503":{"rewardMult":"4% + 0.00% BONUS","planetValue":"5572257","dailyRewards":"222890","totalClaimed":"3744378","tofuLink":"https://tofunft.com/nft/avax/0x89323f00a621D4eD6A56a93295C5f10f4df57FFa/503"},"566":{"rewardMult":"4% + 0.00% BONUS","planetValue":"5138024","dailyRewards":"205521","totalClaimed":"4037472","tofuLink":"https://tofunft.com/nft/avax/0x89323f00a621D4eD6A56a93295C5f10f4df57FFa/566"},"766":{"rewardMult":"4% + 0.00% BONUS","planetValue":"4596551","dailyRewards":"183862","totalClaimed":"3035194","tofuLink":"https://tofunft.com/nft/avax/0x89323f00a621D4eD6A56a93295C5f10f4df57FFa/766"}}}