{"lastUpdated":1643729582286,"pendingReflectionsLastTwoHoursInUSD":2.578536854442897,"pendingReflectionsLastTwoHoursInETH":0.0009351469719017093,"pendingReflectionsLastTwentyFourHoursInUSD":1436.2384641584686,"pendingReflectionsLastTwentyFourHoursInETH":0.5208744828961284,"circulatingICYSupplyInUSD":743180.9753981979,"liquidityInUSD":96249.25369253542,"treasuryValueInUSD":18425.393311214244,"insurancePercentage":0.191434142129283,"reflectionTreasuryBalanceInUSD":96153.42966900773,"reflectionTreasuryBalanceInETH":34.87155455544714,"circulatingICYSupply":726813225907296.5,"pricePerETH":"2757.36","pricePerAVAX":"70.265","pricePerICY":1.0225198839364394e-9,"ICYMarketCap":1022519.8839364394,"ICY2HourVolume":80.0415679156154,"ICY24HourVolume":8370.67,"ETHDistributedInUSD":280774.82789214264,"ETHDistributed":101.74235926902092,"deposits":[0,532.40845001604,47.84445708318739,149.90368924210262,56.28560294014196],"planetData":{"96":{"rewardMult":"4% + 0.00% BONUS","planetValue":"4530676","dailyRewards":"181227","totalClaimed":"515772","tofuLink":"https://tofunft.com/nft/avax/0x89323f00a621D4eD6A56a93295C5f10f4df57FFa/96"},"503":{"rewardMult":"4% + 0.00% BONUS","planetValue":"5572257","dailyRewards":"222890","totalClaimed":"701702","tofuLink":"https://tofunft.com/nft/avax/0x89323f00a621D4eD6A56a93295C5f10f4df57FFa/503"},"566":{"rewardMult":"4% + 0.00% BONUS","planetValue":"5138024","dailyRewards":"205521","totalClaimed":"1231906","tofuLink":"https://tofunft.com/nft/avax/0x89323f00a621D4eD6A56a93295C5f10f4df57FFa/566"},"766":{"rewardMult":"4% + 0.00% BONUS","planetValue":"4596551","dailyRewards":"183862","totalClaimed":"525293","tofuLink":"https://tofunft.com/nft/avax/0x89323f00a621D4eD6A56a93295C5f10f4df57FFa/766"}}}