{"lastUpdated":1644853995263,"pendingReflectionsLastTwoHoursInUSD":4.588371552968519,"pendingReflectionsLastTwoHoursInETH":0.0015610157187706533,"pendingReflectionsLastTwentyFourHoursInUSD":1974.2279642258165,"pendingReflectionsLastTwentyFourHoursInETH":0.671654605346698,"circulatingICYSupplyInUSD":225780.62988874307,"liquidityInUSD":57103.646106152846,"treasuryValueInUSD":25463.05224008963,"insurancePercentage":0.4459093941699463,"reflectionTreasuryBalanceInUSD":57195.38067177241,"reflectionTreasuryBalanceInETH":19.458513165078134,"circulatingICYSupply":722784875187955.4,"pricePerETH":"2939.35","pricePerAVAX":"81.02","pricePerICY":3.123759747048253e-10,"ICYMarketCap":312375.9747048253,"ICY2HourVolume":111.85845947889496,"ICY24HourVolume":15037.2,"ETHDistributedInUSD":310632.18648722547,"ETHDistributed":105.86136749691597,"deposits":[0,816.899776906559,84.26289960453437,305.083200512681,211.98192487882906],"planetData":{"96":{"rewardMult":"4% + 0.00% BONUS","planetValue":"4530676","dailyRewards":"181227","totalClaimed":"2465593","tofuLink":"https://tofunft.com/nft/avax/0x89323f00a621D4eD6A56a93295C5f10f4df57FFa/96"},"503":{"rewardMult":"4% + 0.00% BONUS","planetValue":"5572257","dailyRewards":"222890","totalClaimed":"3099779","tofuLink":"https://tofunft.com/nft/avax/0x89323f00a621D4eD6A56a93295C5f10f4df57FFa/503"},"566":{"rewardMult":"4% + 0.00% BONUS","planetValue":"5138024","dailyRewards":"205521","totalClaimed":"3443106","tofuLink":"https://tofunft.com/nft/avax/0x89323f00a621D4eD6A56a93295C5f10f4df57FFa/566"},"766":{"rewardMult":"4% + 0.00% BONUS","planetValue":"4596551","dailyRewards":"183862","totalClaimed":"2503465","tofuLink":"https://tofunft.com/nft/avax/0x89323f00a621D4eD6A56a93295C5f10f4df57FFa/766"}}}