{"lastUpdated":1645397016995,"pendingReflectionsLastTwoHoursInUSD":0,"pendingReflectionsLastTwoHoursInETH":0,"pendingReflectionsLastTwentyFourHoursInUSD":138.6718838794004,"pendingReflectionsLastTwentyFourHoursInETH":0.053082686780956186,"circulatingICYSupplyInUSD":271730.9242196363,"liquidityInUSD":61276.60349480079,"treasuryValueInUSD":18954.401624782167,"insurancePercentage":0.30932526517058695,"reflectionTreasuryBalanceInUSD":61276.56754296671,"reflectionTreasuryBalanceInETH":23.45626778045522,"circulatingICYSupply":721756523026137.1,"pricePerETH":"2612.375","pricePerAVAX":"77.08","pricePerICY":3.7648558142618414e-10,"ICYMarketCap":376485.58142618416,"ICY2HourVolume":1.2650066130152358e-10,"ICY24HourVolume":767.75,"ETHDistributedInUSD":278005.6447258949,"ETHDistributed":106.423624311522,"deposits":[0,916.7730415258322,143.35663726048296,344.09888720212086,218.51561431063817],"planetData":{"96":{"rewardMult":"4% + 0.00% BONUS","planetValue":"4530676","dailyRewards":"181227","totalClaimed":"2950149","tofuLink":"https://tofunft.com/nft/avax/0x89323f00a621D4eD6A56a93295C5f10f4df57FFa/96"},"503":{"rewardMult":"4% + 0.00% BONUS","planetValue":"5572257","dailyRewards":"222890","totalClaimed":"3695732","tofuLink":"https://tofunft.com/nft/avax/0x89323f00a621D4eD6A56a93295C5f10f4df57FFa/503"},"566":{"rewardMult":"4% + 0.00% BONUS","planetValue":"5138024","dailyRewards":"205521","totalClaimed":"3992617","tofuLink":"https://tofunft.com/nft/avax/0x89323f00a621D4eD6A56a93295C5f10f4df57FFa/566"},"766":{"rewardMult":"4% + 0.00% BONUS","planetValue":"4596551","dailyRewards":"183862","totalClaimed":"2995066","tofuLink":"https://tofunft.com/nft/avax/0x89323f00a621D4eD6A56a93295C5f10f4df57FFa/766"}}}