{"lastUpdated":1643502191438,"pendingReflectionsLastTwoHoursInUSD":0,"pendingReflectionsLastTwoHoursInETH":0,"pendingReflectionsLastTwentyFourHoursInUSD":4613.795547684536,"pendingReflectionsLastTwentyFourHoursInETH":1.770413727908481,"circulatingICYSupplyInUSD":900084.8239079054,"liquidityInUSD":105086.0216537028,"treasuryValueInUSD":17483.816872968368,"insurancePercentage":0.16637623727524858,"reflectionTreasuryBalanceInUSD":104991.09987517961,"reflectionTreasuryBalanceInETH":40.28736917493285,"circulatingICYSupply":726839060050752.5,"pricePerETH":"2606.055","pricePerAVAX":"71.92","pricePerICY":1.2383550546183577e-9,"ICYMarketCap":1238355.0546183577,"ICY2HourVolume":620.0211003749686,"ICY24HourVolume":30876.42,"ETHDistributedInUSD":262333.57065117307,"ETHDistributed":100.66309830420812,"deposits":[0,582.0155147069199,0,164.7463222085477,61.85869156136814],"planetData":{"96":{"rewardMult":"4% + 10.00% BONUS","planetValue":"4530676","dailyRewards":"634295","totalClaimed":"0","tofuLink":"https://tofunft.com/nft/avax/0x89323f00a621D4eD6A56a93295C5f10f4df57FFa/96"},"503":{"rewardMult":"4% + 9.50% BONUS","planetValue":"5572257","dailyRewards":"752255","totalClaimed":"54373","tofuLink":"https://tofunft.com/nft/avax/0x89323f00a621D4eD6A56a93295C5f10f4df57FFa/503"},"566":{"rewardMult":"4% + 1.00% BONUS","planetValue":"5138024","dailyRewards":"256901","totalClaimed":"640262","tofuLink":"https://tofunft.com/nft/avax/0x89323f00a621D4eD6A56a93295C5f10f4df57FFa/566"},"766":{"rewardMult":"4% + 6.00% BONUS","planetValue":"4596551","dailyRewards":"459655","totalClaimed":"0","tofuLink":"https://tofunft.com/nft/avax/0x89323f00a621D4eD6A56a93295C5f10f4df57FFa/766"}}}